sensirion_uart_sfx6xxx/__init__.py
sensirion_uart_sfx6xxx/commands.py
sensirion_uart_sfx6xxx/device.py
sensirion_uart_sfx6xxx/response_provider.py
sensirion_uart_sfx6xxx/result_types.py
sensirion_uart_sfx6xxx/version.py
sensirion_uart_sfx6xxx-1.0.0.dist-info/LICENSE
sensirion_uart_sfx6xxx-1.0.0.dist-info/METADATA
sensirion_uart_sfx6xxx-1.0.0.dist-info/WHEEL
sensirion_uart_sfx6xxx-1.0.0.dist-info/top_level.txt
sensirion_uart_sfx6xxx-1.0.0.dist-info/RECORD
